{
  "$schema": "https://mintlify.com/docs.json",
  "theme": "mint",
  "name": "그릿의 개발 블로그",
  "colors": {
    "primary": "#16A34A",
    "light": "#07C983",
    "dark": "#15803D"
  },

  "favicon": "/favicon.svg",
  "styling": {
    "eyebrows": "breadcrumbs"
  },
  "navigation": {
    "tabs": [
      {
        "tab": "기술 도서",
        "groups": [
          {
            "group": "리액트",
            "pages": [
              {
                "group": "리액트 훅을 활용한 상태 관리",
                "pages": ["books/react/리액트 훅을 활용한 상태 관리/5장"]
              }
            ]
          }
        ]
      },
      {
        "tab": "학습 정리(TIL)",
        "groups": [
          {
            "group": "리액트"
          }
        ]
      }
    ]
  },
  "logo": {
    "light": "/logo/light.svg",
    "dark": "/logo/dark.svg"
  },
  "navbar": {
    "primary": {
      "type": "button",
      "label": "Dashboard",
      "href": "https://dashboard.mintlify.com"
    }
  },

  "footer": {
    "socials": {
      "github": "https://github.com/Grit03"
    }
  }
}
